LICENSE
MANIFEST.in
README
requirements.txt
setup.py
smoothtest/ColorStreamHandler.py
smoothtest/HTMLTestRunner.py
smoothtest/IpythonEmbedder.py
smoothtest/Logger.py
smoothtest/TestResults.py
smoothtest/TestRunner.py
smoothtest/__init__.py
smoothtest/base.py
smoothtest/import_unittest.py
smoothtest/singleton_decorator.py
smoothtest/utils.py
smoothtest.egg-info/PKG-INFO
smoothtest.egg-info/SOURCES.txt
smoothtest.egg-info/dependency_links.txt
smoothtest.egg-info/requires.txt
smoothtest.egg-info/top_level.txt
smoothtest/autotest/Command.py
smoothtest/autotest/Main.py
smoothtest/autotest/Master.py
smoothtest/autotest/Slave.py
smoothtest/autotest/SourceWatcher.py
smoothtest/autotest/TestRunner.py
smoothtest/autotest/TestSearcher.py
smoothtest/autotest/__init__.py
smoothtest/autotest/__test.py
smoothtest/autotest/base.py
smoothtest/autotest/ipython_extension.py
smoothtest/autotest/tests/__init__.py
smoothtest/autotest/tests/test_base.py
smoothtest/commands/smoothtest
smoothtest/commands/smtest
smoothtest/demos/__init__.py
smoothtest/demos/search_engines_demo.py
smoothtest/demos/simple_demo.py
smoothtest/demos/xpath_browser_demo.py
smoothtest/demos/chat_example/__init__.py
smoothtest/demos/chat_example/chat_example.py
smoothtest/demos/chat_example/test_chat_example.py
smoothtest/discover/ModuleAttrIterator.py
smoothtest/discover/SmokeTestDiscover.py
smoothtest/discover/TestDiscover.py
smoothtest/discover/__init__.py
smoothtest/settings/__init__.py
smoothtest/settings/default.py
smoothtest/settings/solve_settings.py
smoothtest/tests/__init__.py
smoothtest/tests/example/__init__.py
smoothtest/tests/example/smoke_test_example.py
smoothtest/tests/example/test_ErroringExample.py
smoothtest/tests/example/test_Example.py
smoothtest/tests/example/test_Example2.py
smoothtest/webunittest/ImagesComparator.py
smoothtest/webunittest/ScreenshotDecorator.py
smoothtest/webunittest/TestCase.py
smoothtest/webunittest/WebdriverManager.py
smoothtest/webunittest/XpathBrowser.py
smoothtest/webunittest/__init__.py
smoothtest/webunittest/tests/__init__.py
smoothtest/webunittest/tests/test_ImagesComparator.py
smoothtest/webunittest/tests/test_XpathBrowser.py