Metadata-Version: 1.0
Name: smoothtest
Version: 0.3.6
Summary: General purpose Testing Utilities and also special testing tools for for Web Applications
Home-page: https://github.com/joaduo/smoothtest
Author: Joaquin Duo
Author-email: joaduo@gmail.com
License: MIT
Keywords: testing,automation,web,unittest
Platform: UNKNOWN
